matrix/__init__.py
matrix/cli.py
matrix-3.0.0.dist-info/AUTHORS.rst
matrix-3.0.0.dist-info/LICENSE
matrix-3.0.0.dist-info/METADATA
matrix-3.0.0.dist-info/WHEEL
matrix-3.0.0.dist-info/top_level.txt
matrix-3.0.0.dist-info/RECORD
